CampyCPS/.DS_Store
CampyCPS/CampyCPS.py
CampyCPS/CampyCPS_core.py
CampyCPS/__init__.py
CampyCPS/db/CAMP1067.fas
CampyCPS/db/CAMP1324.fas
CampyCPS/db/CAMP1325.fas
CampyCPS/db/CAMP1326.fas
CampyCPS/db/CAMP1327.fas
CampyCPS/db/CAMP1328.fas
CampyCPS/db/CAMP1329.fas
CampyCPS/db/CAMP1330.fas
CampyCPS/db/CAMP1331.fas
CampyCPS/db/CAMP1332.fas
CampyCPS/db/CAMP1333.fas
CampyCPS/db/CAMP1334.fas
CampyCPS/db/CAMP1335.fas
CampyCPS/db/CAMP1336.fas
CampyCPS/db/CAMP1337.fas
CampyCPS/db/CAMP1338.fas
CampyCPS/db/CAMP1339.fas
CampyCPS/db/CAMP1340.fas
CampyCPS/db/CAMP1341.fas
CampyCPS/db/CAMP1342.fas
CampyCPS/db/CAMP1343.fas
CampyCPS/db/CAMP1344.fas
CampyCPS/db/CAMP1345.fas
CampyCPS/db/CAMP1346.fas
CampyCPS/db/CAMP1347.fas
CampyCPS/db/CAMP1348.fas
CampyCPS/db/CAMP1349.fas
CampyCPS/db/CAMP1350.fas
CampyCPS/db/CAMP1351.fas
CampyCPS/db/CAMP1352.fas
CampyCPS/db/CAMP1353.fas
CampyCPS/db/CAMP1354.fas
CampyCPS/db/CAMP1355.fas
CampyCPS/db/CAMP1356.fas
CampyCPS/db/CAMP1357.fas
CampyCPS/db/CAMP1358.fas
CampyCPS/db/CPS_scheme.csv
CampyCPS/db/CPS_scheme.xlsx
CampyCPS/db/CampyCPS.fa
CampyCPS-1.0.3.dist-info/METADATA
CampyCPS-1.0.3.dist-info/WHEEL
CampyCPS-1.0.3.dist-info/entry_points.txt
CampyCPS-1.0.3.dist-info/top_level.txt
CampyCPS-1.0.3.dist-info/RECORD
