Metadata-Version: 2.1
Name: CampyCPS
Version: 1.0.3
Summary: Campylobacter CPS relevant gene analysis tool
Home-page: https://github.com/hbucqp/CampyCPS
Author: Qingpo Cui
Author-email: cqp@cau.edu.cn
License: MIT Licence
Keywords: wgs,Campylobacter CPS
Platform: any
Classifier: Development Status :: 3 - Alpha
Classifier: Intended Audience :: Developers
Classifier: Topic :: Software Development :: Build Tools
Classifier: License :: OSI Approved :: MIT License
Classifier: Programming Language :: Python :: 3.8
Classifier: Programming Language :: Python :: 3.9
Classifier: Programming Language :: Python :: 3.10
Classifier: Programming Language :: Python :: 3.11
Requires-Dist: Bio
Requires-Dist: pandas
Requires-Dist: setuptools
